Metadata-Version: 2.1
Name: mail-sendgrid
Version: 1.0.1
Summary: Cli tool for send mail over sendgrid
Home-page: https://github.com/hardwario/mail-sendgrid
Author: HARDWARIO s.r.o.
Author-email: ask@hardwario.com
License: MIT
Keywords: cooper influxdb iot
Platform: any
Classifier: Development Status :: 5 - Production/Stable
Classifier: Environment :: Console
Classifier: Intended Audience :: Developers
Classifier: License :: OSI Approved :: MIT License
Classifier: Natural Language :: English
Classifier: Operating System :: OS Independent
Classifier: Programming Language :: Python :: 3
Classifier: Topic :: Utilities
